dicio/__init__.py
dicio/dicio.py
dicio/utils.py
Dicio-1.3.0.dist-info/LICENSE
Dicio-1.3.0.dist-info/METADATA
Dicio-1.3.0.dist-info/WHEEL
Dicio-1.3.0.dist-info/top_level.txt
Dicio-1.3.0.dist-info/RECORD
