Metadata-Version: 2.1
Name: Dicio
Version: 1.3.0
Summary: Unofficial Python API for Dicio.
Home-page: https://github.com/felipemfp/dicio
Author: Felipe Pontes
Author-email: felipemfpontes@gmail.com
License: MIT License
Platform: UNKNOWN
Classifier: Development Status :: 4 - Beta
Classifier: License :: OSI Approved :: MIT License
Classifier: Programming Language :: Python
Classifier: Programming Language :: Python :: 3 :: Only
Classifier: Topic :: Internet :: WWW/HTTP :: Browsers
Classifier: Topic :: Internet :: WWW/HTTP :: Indexing/Search
Classifier: Topic :: Utilities
